<?xml version="1.0" encoding="utf-8"?>
<LanguageData>
  <OARK_SDBirthdayVisit.questDescriptionRules.rulesStrings>
    <li>questDescription(uniqueQuestDesc!=True)-&gt;[approachInfo] [claimInfo] [asker_nameDef](은)는 [lodgersPronoun](이)가 재정비할 수 있도록 [map_definite]에 [questDurationTicks_duration] 동안 머물게 해달라고 요청했습니다.\n\n보답으로, 이 기간 동안 [lodgersPronoun](은)는 당신을 위해 무보수로 일하고 전투에 참여하겠다고 [offer].\n\n[joinInfo] [futureRewardInfo]\n\n[playerBetrayInfo]</li>
    <li>offer(lodgerCount==1)-&gt;제안했습니다</li>
    <li>offer(lodgerCount&gt;=2)-&gt;제안했습니다</li>
    <li>lodgersPronoun(lodgerCount==1)-&gt;[asker_pronoun]</li>
    <li>lodgersPronoun(lodgerCount&gt;=2)-&gt;그녀들은</li>
    <li>lodgersPreposition(lodgerCount==1)-&gt;[asker_objective] 자신</li>
    <li>lodgersPreposition(lodgerCount&gt;=2)-&gt;그녀들 자신</li>
    <li>lodgersObjective(lodgerCount==1)-&gt;[asker_objective]</li>
    <li>lodgersObjective(lodgerCount&gt;=2)-&gt;그녀들을</li>
    <li>lodgersPossessive(lodgerCount==1)-&gt;[asker_possessive]</li>
    <li>lodgersPossessive(lodgerCount&gt;=2)-&gt;그녀들의</li>
    <li>lodgersSingularOrPluralDef(lodgerCount==1)-&gt;[asker_nameDef]</li>
    <li>lodgersSingularOrPluralDef(lodgerCount&gt;=2)-&gt;[lodgersLabelPlural]</li>
    <li>travelerInfo(lodgerCount==1)-&gt;이 [faction_pawnSingular]</li>
    <li>travelerInfo(lodgerCount&gt;=2)-&gt;이 [faction_pawnsPlural]</li>
    <li>joinInfo(allowJoinOffer!=True)-&gt;</li>
    <li>joinInfo(allowJoinOffer==True,lodgerCount==1)-&gt;당신이 [asker_objective]의 기분을 높게 유지한다면, [asker_pronoun](이)가 당신에게 합류를 제안할지도 모릅니다.</li>
    <li>joinInfo(allowJoinOffer==True,lodgerCount&gt;=2)-&gt;당신이 그녀들의 기분을 높게 유지한다면, 그중 일부가 당신에게 합류를 제안할지도 모릅니다.</li>
    <li>futureRewardInfo(allowFutureReward!=True)-&gt;</li>
    <li>futureRewardInfo(allowFutureReward==True)-&gt;[lodgersPronoun] 나중에 [lodgersObjective] 도와준 것에 대해 당신에게 보상할 수도 있습니다.</li>
    <li>playerBetrayInfo(isMainFaction!=True)-&gt;[travelerInfo](은)는 어느 주요 파벌에도 속해 있지 않습니다. 원한다면 외교적 불이익 없이 [lodgersObjective](을)를 살해, 체포, 판매하거나 장기를 적출할 수 있습니다.</li>
    <li>playerBetrayInfo(isMainFaction==True)-&gt;[travelerInfo](은)는 [asker_factionName] 소속입니다. [lodgersObjective](을)를 살해, 체포, 판매하거나 장기를 적출할 경우 매우 심각한 외교적 불이익이 발생할 것입니다.</li>
    <li>questDescription-&gt;[faction_name]의 과학 부서로부터 긴급 메시지를 받았습니다. 발신자는 해당 부서의 [asker_nameDef]입니다.\n\n[asker_nameDef]의 말에 따르면, 최근 정착지와 과학 부서 간의 협력 과정에서 [birthdayPawnsInfo](이)가 부서의 수행원들과 함께 [yuanyin] 깊은 우정을 쌓았다고 합니다.\n어제 일정을 검토하던 중, 그들은 뜻밖에도 오늘이 [birthdayPawnsInfo]의 생일이라는 사실을 깨달았습니다. 오베로니아 아우레아의 전통 축제 관습에 따라, 그들은 몇 번의 "합리적인 실험 실패"를 감수하고 [birthdayPawnsInfo](을)를 위한 선물을 준비했으며, 오늘 정착지를 방문할 계획을 세웠습니다. 하지만 출발 직전에야 방문 요청을 보내야 한다는 것을 간신히 떠올린 모양입니다.\n\n이들의 방문 요청을 수락하면, 그들은 즉시 정착지에 도착하여 속을 꽉 채운 꽃떡을 축하 선물로 건넬 것입니다. 머무는 동안 그들은 생일 주인공에게 축복과 선의를 전하며 기분을 높여줄 것입니다.</li>
    <li>yuanyin-&gt;조정관을 속이기 위해 회계 장부를 정리하며</li>
    <li>yuanyin-&gt;과학 부서 내의 미묘하고도 말 못 할 로맨스에 대해 토론하며</li>
    <li>yuanyin-&gt;히아신스 연구관의 트윈테일이 실제로 채굴용 드릴로 쓰일 수 있는지 연구하며</li>
    <li>yuanyin-&gt;기술 부서의 비행 쟁반을 개선하고 테스트하는 것을 도우며</li>
    <li>yuanyin-&gt;사고로 인해 또다시 여행 계획이 연기된 큰물망초 연구관에게 위로를 건네며</li>
    <li>yuanyin-&gt;형형색색의 스파게티가 지닌 실현 가능성과 식중독 확률에 대해 고민하며</li>
    <li>yuanyin-&gt;부적절한 사용으로 고장 난 과학 부서의 실험 장비들을 유지보수하며</li>
    <li>yuanyin-&gt;소량의 오베로니아 아우레아 꽃떡과 다량의 정체불명 음식물 쓰레기를 만들어내며</li>
    <li>yuanyin-&gt;지역사회에 떠도는 기괴한 식품 안전 루머에 대해 논의하며</li>
    <li>yuanyin-&gt;서로에게 영감을 주기 위해 연구 관점을 교환하며</li>
    <li>yuanyin-&gt;반중력 기술에 대한 토론과 연구를 진행하며</li>
  </OARK_SDBirthdayVisit.questDescriptionRules.rulesStrings>
</LanguageData>