<?xml version="1.0" encoding="UTF-8"?>
<LanguageData>
  
  <!-- EN:
    <li>questDescription->We have observed a concentration of abundant solar crystal under the solar flare. Send a caravan to mine it.</li>
  -->
  <Milira_SolarCrystalMining.questDescriptionRules.rulesStrings><li>questDescription->태양 흑점 폭발 때 풍부한 태양 수정이 집중되어 있는 것을 관측했습니다. 상단을 보내 채굴하세요.</li></Milira_SolarCrystalMining.questDescriptionRules.rulesStrings>
  <!-- EN:
    <li>questName->Lump of Solar Crystal</li>
  -->
  <Milira_SolarCrystalMining.questNameRules.rulesStrings><li>questName->태양 수정 결정</li></Milira_SolarCrystalMining.questNameRules.rulesStrings>
  <!-- EN: quest expired: [resolvedQuestName] -->
  <Milira_SolarCrystalMining.root.nodes.WorldObjectTimeout.node.nodes.Letter.label.slateRef>임무 만료: [resolvedQuestName]</Milira_SolarCrystalMining.root.nodes.WorldObjectTimeout.node.nodes.Letter.label.slateRef>
  <!-- EN: The Solar Crystal has been mined already, the quest ‘[resolvedQuestName]’ has expired. -->
  <Milira_SolarCrystalMining.root.nodes.WorldObjectTimeout.node.nodes.Letter.text.slateRef>태양 수정이 채굴되어, ‘[resolvedQuestName]’ 임무가 만료되었습니다.</Milira_SolarCrystalMining.root.nodes.WorldObjectTimeout.node.nodes.Letter.text.slateRef>
  
</LanguageData>