<?xml version="1.0" encoding="utf-8"?>
<LanguageData>
  <DialectLearned_Exalted.stages.0.label>방언 학습함</DialectLearned_Exalted.stages.0.label>
  <DialectLearned_Exalted.stages.0.description>글자가 모여 단어를 만들고, 단어가 모여 시를 완성하지.</DialectLearned_Exalted.stages.0.description>
  <LanguageLearned_Exalted.stages.0.label>언어 학습함</LanguageLearned_Exalted.stages.0.label>
  <LanguageLearned_Exalted.stages.0.description>글자가 모여 단어를 만들고, 단어가 모여 시를 완성하지.</LanguageLearned_Exalted.stages.0.description>
  <LanguageExperienceGain_Exalted.stages.0.label>낯선 언어 접함</LanguageExperienceGain_Exalted.stages.0.label>
  <LanguageExperienceGain_Exalted.stages.0.description>한 걸음씩 나아가다 보면, 우리는 진리를 배우게 될 거야.</LanguageExperienceGain_Exalted.stages.0.description>
  <DialectLearned_Encouraged.stages.0.label>방언 학습함</DialectLearned_Encouraged.stages.0.label>
  <DialectLearned_Encouraged.stages.0.description>글자가 모여 단어를 만들고, 단어가 모여 시를 완성하지.</DialectLearned_Encouraged.stages.0.description>
  <LanguageLearned_Encouraged.stages.0.label>언어 학습함</LanguageLearned_Encouraged.stages.0.label>
  <LanguageLearned_Encouraged.stages.0.description>글자가 모여 단어를 만들고, 단어가 모여 시를 완성하지.</LanguageLearned_Encouraged.stages.0.description>
  <LanguageExperienceGain_Encouraged.stages.0.label>낯선 언어 접함</LanguageExperienceGain_Encouraged.stages.0.label>
  <LanguageExperienceGain_Encouraged.stages.0.description>한 걸음씩 나아가다 보면, 우리는 진리를 배우게 될 거야.</LanguageExperienceGain_Encouraged.stages.0.description>
  <DialectLearned_Condemned.stages.0.label>방언 학습함</DialectLearned_Condemned.stages.0.label>
  <DialectLearned_Condemned.stages.0.description>어쩌구 저쩌구… 걔네가 할 줄 아는 게 이게 다야?</DialectLearned_Condemned.stages.0.description>
  <LanguageLearned_Condemned.stages.0.label>언어 학습함</LanguageLearned_Condemned.stages.0.label>
  <LanguageLearned_Condemned.stages.0.description>멍청한 횡설수설이야...</LanguageLearned_Condemned.stages.0.description>
  <LanguageExperienceGain_Condemned.stages.0.label>낯선 언어 접함</LanguageExperienceGain_Condemned.stages.0.label>
  <LanguageExperienceGain_Condemned.stages.0.description>귀만 아픈 헛소리.</LanguageExperienceGain_Condemned.stages.0.description>
  <DialectLearned_Hatred.stages.0.label>방언 학습함</DialectLearned_Hatred.stages.0.label>
  <DialectLearned_Hatred.stages.0.description>세상에, 이게 말이냐?</DialectLearned_Hatred.stages.0.description>
  <LanguageLearned_Hatred.stages.0.label>언어 학습함</LanguageLearned_Hatred.stages.0.label>
  <LanguageLearned_Hatred.stages.0.description>듣기만 해도 토 나와…</LanguageLearned_Hatred.stages.0.description>
  <LanguageExperienceGain_Hatred.stages.0.label>낯선 언어 접함</LanguageExperienceGain_Hatred.stages.0.label>
  <LanguageExperienceGain_Hatred.stages.0.description>역겹기만 한데, 왜 배워야 하는 거지?</LanguageExperienceGain_Hatred.stages.0.description>
</LanguageData>