<?xml version="1.0" encoding="utf-8"?>
<LanguageData>
  <MI_WarriorCulture_Accepted.label>수용됨</MI_WarriorCulture_Accepted.label>
  <MI_WarriorCulture_Accepted.description>이 사회는 강인한 전사 문화로 발전했습니다. 무용은 그 무엇보다 가치 있게 여겨지며, 진정한 영광은 오직 전장에서만 찾을 수 있습니다.\n\n동시에, 이 사회는 약하거나 싸울 능력이 없는 이들에 대해서는 관용과 보호의 태도를 취합니다.</MI_WarriorCulture_Accepted.description>
  <MI_WarriorCulture_Accepted.comps.0.description>전사 문화</MI_WarriorCulture_Accepted.comps.0.description>
  <MI_WarriorCulture_Not.label>수용되지 않음</MI_WarriorCulture_Not.label>
  <MI_WarriorCulture_Not.description>이 규율은 수용되지 않습니다.</MI_WarriorCulture_Not.description>
</LanguageData>