<?xml version="1.0" encoding="utf-8"?>
<LanguageData>
  <IATC_Milk_Childhood.title>속죄자</IATC_Milk_Childhood.title>
  <IATC_Milk_Childhood.titleShort>속죄자</IATC_Milk_Childhood.titleShort>
  <IATC_Milk_Childhood.description>밀크는 어린 시절 다른 랫킨들과 다를 바 없는 평범한 아이였습니다. 하지만 어느 날 습격을 받아 랫킨 군벌에게 붙잡혔고, 특공대로 훈련받기 시작했습니다. 그곳에서 지옥 같은 훈련을 견디며 수많은 동족의 죽음을 목격했고, 대신 실력만큼은 독보적인 수준으로 갈고닦았습니다. 결국 이런 삶에 회의를 느낀 밀크는 자신의 죄를 씻기 위해 탈출했습니다.</IATC_Milk_Childhood.description>

  <IATC_Milk_Adulthood.title>괴물 사냥꾼</IATC_Milk_Adulthood.title>
  <IATC_Milk_Adulthood.titleShort>괴물 사냥꾼</IATC_Milk_Adulthood.titleShort>
  <IATC_Milk_Adulthood.description>밀크는 자신이 알던 곳이 아닌 낯선 세계의 바위 해변에서 눈을 떴습니다. 그녀는 속죄의 길에서 벗어나 타락한 영역으로 떨어졌고, 귓가에는 정체모를 괴물들의 포효와 멀리서 울려 퍼지는 사냥총 소리만이 가득했습니다. 오직 손에 쥔 번뜩이는 소총만이 그녀의 곁을 지키는 가운데, 그녀의 이야기는 다시 계속됩니다.</IATC_Milk_Adulthood.description>
</LanguageData>