<?xml version="1.0" encoding="utf-8"?>
<LanguageData>
  <JfdSproutBerry.description>요정나무 주변에 산딸기 덤불이 싹트게 됩니다.</JfdSproutBerry.description>
  <JfdSproutBerry.extraPredictedOutcomeDescriptions.0>품질이 높을 수록 산딸기 덤불이 더욱 많이 나타납니다.</JfdSproutBerry.extraPredictedOutcomeDescriptions.0>
  <JfdSproutBerry.comps.0.label>참여자 수</JfdSproutBerry.comps.0.label>
  <JfdSproutHealroot.description>요정나무 주변에 야생 약뿌리가 싹트게 됩니다.</JfdSproutHealroot.description>
  <JfdSproutHealroot.extraPredictedOutcomeDescriptions.0>의식의 품질이 높을 수록 야생 약뿌리가 더욱 많이 나타납니다.</JfdSproutHealroot.extraPredictedOutcomeDescriptions.0>
  <JfdSproutHealroot.comps.0.label>참여자 수</JfdSproutHealroot.comps.0.label>
</LanguageData>