<?xml version="1.0" encoding="utf-8"?>
<LanguageData>
  <FloatDebugLog>디버그 로그 표시</FloatDebugLog>
  <FloatAGRegen>회피 경로 재계산</FloatAGRegen>
  <FloatFactionFixItems1>세력 관계 수정</FloatFactionFixItems1>
  <FloatFactionFixItems2>세력 지도자 수정</FloatFactionFixItems2>
  <FloatToolsItems1>가축 관계 정리</FloatToolsItems1>
  <FloatToolsItems2>오물 청소 (주거 구역)</FloatToolsItems2>
  <FloatToolsItems2Dev1>개발자 모드: 오물 청소 (현재 지도)</FloatToolsItems2Dev1>
  <FloatToolsItems2Dev2>개발자 모드: 오물 청소 (모든 지도)</FloatToolsItems2Dev2>
  <FloatToolsItems2Snow>눈 청소 (주거 구역)</FloatToolsItems2Snow>
  <FloatToolsItems2SnowDev1>개발자 모드: 눈 청소 (현재 지도)</FloatToolsItems2SnowDev1>
  <FloatToolsItems2SnowDev2>개발자 모드: 눈 청소 (모든 지도)</FloatToolsItems2SnowDev2>
  <FloatToolsItems3>현재 지도 내에 있는 시체 제거</FloatToolsItems3>
  <FloatToolsItems4>전투 기록 삭제</FloatToolsItems4>
  <FloatToolsItems5>고정되지 않은 메세지 삭제</FloatToolsItems5>
  <FloatToolsItems5Dev>개발자 모드: 모든 메세지 삭제</FloatToolsItems5Dev>
  <FloatToolsItems6>현재 지도 내에 있는 썩거나 백골인 시체 제거</FloatToolsItems6>
  <StorytellerFixQueueInfo>이야기꾼 대기열 정보</StorytellerFixQueueInfo>
  <StorytellerFixQueueClearDev>개발자 모드: 이야기꾼 대기열 지우기</StorytellerFixQueueClearDev>
  <QuickCloseLetStack>모든 메세지 닫기</QuickCloseLetStack>
  <QuickUnlockSpeedLimit>배속 제한 해제</QuickUnlockSpeedLimit>
  <QuickOpenSettings>RuntimeGC 설정 변경</QuickOpenSettings>
  <FloatACModMetaData>불필요한 모드 정보 삭제</FloatACModMetaData>
  <FloatACLanguageData>사용하지 않는 번역 삭제</FloatACLanguageData>
  <FloatACDefPackage>캐시된 DefPackage 삭제</FloatACDefPackage>
  <FloatACModMetaDataCleared>현재 불필요한 모드 정보 삭제가 필요하지 않습니다</FloatACModMetaDataCleared>
  <FloatACLanguageDataCleared>현재 사용하지 않는 번역 삭제가 필요하지 않습니다</FloatACLanguageDataCleared>
  <FloatACDefPackageCleared>현재 캐시된 DefPackage 삭제가 필요하지 않습니다</FloatACDefPackageCleared>
  <STFteller>이야기꾼: {0}</STFteller>
  <STFdifficulty>현재 난이도: {0}</STFdifficulty>
  <SFTlength>이야기꾼 대기열 길이: {0}</SFTlength>
  <STFcurrent>현재 작업 대기열: {0}</STFcurrent>
  <STFjobdone>완료된 작업: {0}</STFjobdone>
  <STFjobNOTdone>완료되지 않은 작업: {0}</STFjobNOTdone>
  <HelpTextGCWP>게임 내 캐릭터 정리 - 비활성화
해당 기능이 저장 파일을 손상시킬 수 있기에 비활성화되었습니다.
</HelpTextGCWP>
  <HelpTextGCV>게임 내 캐릭터 정리 - 개발자 모드 한정 허용

반드시 필요한 경우에만 사용하십시오.</HelpTextGCV>
  <HelpTextQB>빠른 작업


모든 메세지 닫기:
모든 메세지를 내용을 읽지 않은 것으로 취급하고 전부 제거합니다. 게으른 사람일 수록 필요한 기능입니다!

배속 제한 해제:
위협이나 습격으로 인해 발생하는 속도 제한 기능을 해제합니다. 이 기능을 사용하더라도 속도 제한이 영구적으로 비활성화되지는 않으며 속도 제한이 걸릴 때 마다 다시 이 기능을 실행하여야 합니다(전체 교전 기간동안 속도 제한을 없애기 위해 존재하는 기능이 아니고 교전 전에 행군하는 시간을 줄이기 위해 설계된 기능입니다).

RuntimeGC 설정 변경:
모드 설정 페이지를 불러옵니다 (HugsLib 모드가 활성화 되어 있을 경우 림월드 기본 모드 페이지).</HelpTextQB>
  <HelpTextAddOn>더 많은 정리


가축 관계 정리:
동물들에겐 때로 너무 많은 관계(죽거나 다른 세력으로 팔려갔거나 등)를 형성할만한 상황이 발생할 수 있으며, 이 기능을 사용하여 해당 관계를 끊어서 정리할 수 있습니다. 게임 내 캐릭터 정리 기능을 사용한 후 사용하는 것을 권장합니다.

오물 제거 (주거구역): 말 그대로.

눈 제거 (주거구역): 위와 동일하지만 눈은 내립니다.

현재 지도에 있는 시체 제거:
무덤에 있거나 동면관에 보관되어 있거나 이와 유사한 상태인 시체는 무시합니다.

전투 기록 삭제:
전투 중에 생성되었던 전투 내역 기록들을 전부 제거합니다.

고정하지 않은 메세지와 알림 기록 제거:
메세지와 알림은 게임이 진행되는 동안 발생하고 기록되며 기록-메세지 탭에서 사라지지 않은 이상은 언제든 추적할 수 있습니다. 이 작업을 수행하게 될 경우 모든 메세지와 알림 기록이 제거되지만 미리 고정해둔 메세지와 알림은 유지됩니다.</HelpTextAddOn>
  <HelpTextFix>응급 처치


디버그 로그 표시:
디버그 로그 창을 불러옵니다. 개발자 모드를 키는 것을 거부하거나 영구적으로 비활성화한 사람들을 배려하기 위한 기능입니다.

회피 경로 재계산:
회피 경로를 재계산하여 일부 습격자들의 AI 문제를 해결하려고 시도합니다.

세력 관계 수정: 디버그 로그에서 나타나는 오류 수정 시도:"Faction xxx has null relation with xxx. Return Dummy relation." 
이 도구는 다음 모드로 인해 발생하는 오류를 수정할 수 없습니다:
1.Misc. FactionBase:Error while generating maps,if a mechanoid is spawned.
2.PPSMedicalCare (불확실함):Error during saving and loading,and that might become increasingly serious.

세력 지도자 변경 시도: 버그 상태에 빠진 세력의 지도자를 재생성하여 통신기에서 발생하는 문제를 해결하려 시도합니다. 정상적인 지도자가 있는 세력들은 영향을 받지 않습니다.</HelpTextFix>
  <HelpTextSysGC>메모리 정리


System.GC.Collect() 명령을 호출하여 사용이 끝난 메모리를 회수합니다. (다른 프로그램에 영향을 주지 않습니다)
게임 성능이 일시적으로 약간 향상됩니다(곧 다시 원래대로 되돌아옵니다).

Shift+클릭: 일부 자동 정리 명령을 수동으로 실행합니다. 자세한 사항은 RuntimeGC 모드 페이지에서 확인하십시오.</HelpTextSysGC>
  <MMUpdate_Debug_Flash>개발자 모드: 실시간 (~0.03초)</MMUpdate_Debug_Flash>
  <MMUpdate_Debug_Realtime>개발자 모드: 매우 빈번함 (~0.25초)</MMUpdate_Debug_Realtime>
  <MMUpdate_PerSecond>빈번하게 (~1초)</MMUpdate_PerSecond>
  <MMUpdate_UltraFrequent>수시로 (~2.5초)</MMUpdate_UltraFrequent>
  <MMUpdate_Frequent>자주 (~5초)</MMUpdate_Frequent>
  <MMUpdate_Moderate>보통 (~10초)</MMUpdate_Moderate>
  <MMUpdate_PerMinuteQuarter>가끔 (~15초)</MMUpdate_PerMinuteQuarter>
  <MMUpdate_PerMinuteHalf>매우 가끔 (~30초)</MMUpdate_PerMinuteHalf>
  <MMUpdate_PerMinute>어쩌다 가끔 (~60초)</MMUpdate_PerMinute>
  <MMUpdate_Debug_Lazy>개발자 모드: 게으르게 (~5분)</MMUpdate_Debug_Lazy>
  <MMUpdate_Debug_frozen>개발자 모드: 방치 (~1년)</MMUpdate_Debug_frozen>
  <MsgTextAGR>RuntimeGC: 모든 맵의 회피 경로가 재계산되었습니다.</MsgTextAGR>
  <MsgTextFFR>RuntimeGC: 세력간 관계가 수정되었습니다.</MsgTextFFR>
  <MsgTextFFL>RuntimeGC: {0}개 세력의 지도자가 교체되었습니다.</MsgTextFFL>
  <MsgTextAFT>RuntimeGC: 가축 관계도의 중복된 구성원 {0}마리 제거됨.</MsgTextAFT>
  <MsgTextRFH>RuntimeGC: 주거 구역에 있는 {0}개의 오물이 청소되었습니다.</MsgTextRFH>
  <MsgTextRFM>RuntimeGC: 현재 지도에 있는 {0}개의 오물이 청소되었습니다.</MsgTextRFM>
  <MsgTextRFW>RuntimeGC: 모든 지도에 있는 {0}개의 오물이 청소되었습니다.</MsgTextRFW>
  <MsgTextRSH>RuntimeGC: 주거 구역의 모든 눈이 청소되었습니다.</MsgTextRSH>
  <MsgTextRSM>RuntimeGC: 현재 지도의 모든 눈이 청소되었습니다.</MsgTextRSM>
  <MsgTextRSW>RuntimeGC: 모든 지도의 모든 눈이 청소되었습니다.</MsgTextRSW>
  <MsgTextRCM>RuntimeGC: 현재 지도에 있는 {0}개의 시체가 삭제되었습니다.</MsgTextRCM>
  <MsgTextRBL>RuntimeGC: {0}개의 전투 기록이 삭제되었습니다.</MsgTextRBL>
  <MsgTextRAM>RuntimeGC: 보관되어 있던 {0}개의 메세지가 삭제되었습니다.</MsgTextRAM>
  <MsgTextSysGC>System.GC: 메모리 회수 완료!</MsgTextSysGC>
  <SettingsMMCategory>메모리 모니터</SettingsMMCategory>
  <SettingsMMBarLabel>메모리 사용량 백분율로 시각화</SettingsMMBarLabel>
  <SettingsMMBarTip>RuntimeGC 탭에 현재 사용중인 메모리 비율을 연구 탭과 비슷하게 시각적으로 표현합니다.

*참고: 해당 그래픽으로 표시된 메모리 사용량은 RimWorld의 .NET VM의 사용량입니다. Unity 프레임워크 및 게임 내부에서 사용되는 메모리는 .NET VM에서 관리되지 않는 메모리이므로 계산에 포함되지 않습니다. 이 시각적인 표현은 전반적으로 게임 성능을 표현하며 메모리 누수를 모니터링하는데 도움이 됩니다.</SettingsMMBarTip>
  <SettingsMMTipLabel>툴팁에 메모리 사용량 표시</SettingsMMTipLabel>
  <SettingsMMTipTip>메모리 사용량이 툴팁에 표시됩니다. RuntimeGC 탭에 마우스를 가져다 대면 확인 할 수 있습니다.

*참고: 해당 그래픽으로 표시된 메모리 사용량은 RimWorld의 .NET VM의 사용량입니다. Unity 프레임워크 및 게임 내부에서 사용되는 메모리는 .NET VM에서 관리되지 않는 메모리이므로 계산에 포함되지 않습니다. 이 시각적인 표현은 전반적으로 게임 성능을 표현하며 메모리 누수를 모니터링하는데 도움이 됩니다.</SettingsMMTipTip>
  <SettingsMMRangeLabel>모니터링 간격 (Mb)</SettingsMMRangeLabel>
  <SettingsMMRangeTip>이 설정은 RuntimeGC 탭에서 시각적으로 표현하고 있는 백분율 바에만 영향을 줍니다.</SettingsMMRangeTip>
  <SettingsMMIntervalLabel>갱신 주기 (간격)</SettingsMMIntervalLabel>
  <SettingsMMIntervalTip>메모리 모니터링이 갱신되는 주기입니다. 갱신 주기 (간격)은 UI 틱을 기반으로 하며 갱신 사이의 주기는 CPU 성능에 따라 변화 할 수 있습니다.

*참고: 너무 자주 갱신하게 되면 많은 메모리 누수가 발생할 수 있습니다.</SettingsMMIntervalTip>
  <SettingsDevOnScreenMemoryUsageLabel>개발자 모드: "RuntimeGC"를 메모리 사용량 데이터로 교체</SettingsDevOnScreenMemoryUsageLabel>
  <SettingsAutoCleanupCategory>자동 정리</SettingsAutoCleanupCategory>
  <SettingsACModMetaDataLabel>불필요한 모드 정보 삭제</SettingsACModMetaDataLabel>
  <SettingsACModMetaDataTip>"Mods" 버튼을 누를 때만 사용되는 모드 정보를 제거합니다. 게임 시작 후 해당 버튼을 눌러 접근하였을 경우 "RuntimeGC" 탭을 누른 후 Shift 키를 누른 상태로 "메모리 정리" 버튼을 눌러서 수동으로 실행 할 수 있습니다.</SettingsACModMetaDataTip>
  <SettingsACLanguageDataLabel>사용하지 않는 언어의 번역 삭제</SettingsACLanguageDataLabel>
  <SettingsACLanguageDataTip>게임이 시작되는 동안 영어와 현재 언어를 제외한 다른 언어 데이터를 읽어오는 것을 제거합니다. 번역 파일은 영향을 받지 않습니다.

*참고: 언어를 변경하려면 해당 기능을 비활성화 한 후 게임을 다시 실행한 다음에 언어를 변경하여야 합니다. 그렇지 않으면 RimWorld가 언어 데이터를 찾지 못합니다. 언어를 자주 전환해야 하는 번역가일 경우 이 항목을 비활성화하는것을 권장합니다.</SettingsACLanguageDataTip>
  <SettingsACDefPackageLabel>캐시된 DefPackage 삭제</SettingsACDefPackageLabel>
  <SettingsACDefPackageTip>게임이 시작되는 동안 발생한 모드별 DefPackage의 캐시 데이터를 제거합니다.

*참고: 스택 제한을 재정의하거나 재료 아이템을 추가하는 모드를 사용하는 경우 모드가 해당 데이터에 접근하려고 시도하다 오류가 발생 할 시(해당 동작이 권장되지 않는 행위라 하더라도) 이 설정을 비활성화하는것을 권장합니다.</SettingsACDefPackageTip>
  <SettingsMuteCategory>교체/기록 기능</SettingsMuteCategory>
  <SettingsMuteGCLabel>내장 GC 교체/강화</SettingsMuteGCLabel>
  <SettingsMuteGCTip>*특별한 사유가 없다면 반드시 활성화하십시오*
내장 GC 클리너를 RuntimeGC로 교체하여 주기적인 지연(게임 내 하루동안 4회)과 잠재적인 저장 오류를 방지합니다. 해당 항목의 독립적 실행행 버전인 MuteGC 모드를 따로 설치 할 필요가 없습니다.</SettingsMuteGCTip>
  <SettingsMuteBLLabel>전투 기록 삭제</SettingsMuteBLLabel>
  <SettingsMuteBLTip>*어떤 수단을 써서라도 TPS를 올려보고 싶을 정도로 필사적이지 않다면 사용하지 않는것을 권장합니다*
전투 기록의 생성, 저장, 불러오기가 일어나지 않도록 전투 기록을 비활성화합니다. 해당 항목의 독립적 실행행 버전인 MuteCL 모드를 따로 설치 할 필요가 없습니다.</SettingsMuteBLTip>
  <SettingsGeneralCategory>일반적인 설정</SettingsGeneralCategory>
  <SettingsArchiveGCLabel>해당 세계의 폰을 정리한 결과를 메세지로 저장합니다.</SettingsArchiveGCLabel>
  <SettingsArchiveGCTip>폰을 성공적으로 정리한 결과를 메세지에 기록합니다. 기록 - 메세지 탭에서 확인이 가능합니다.
참고: 이 메세지 탭은 200개까지 기록되며 게임 내 알람과 공유됩니다. 한도를 초과하면 이전 기록이 제거됩니다.</SettingsArchiveGCTip>
  <SettingsArchiveGeneralLabel>RuntimeGC의 모든 기록 저장</SettingsArchiveGeneralLabel>
  <SettingsArchiveGeneralTip>*권장하지 않습니다*
RuntimeGC 모드의 모든 알림을 메세지로 저장합니다. 이로 인해 게임 내의 대량의 메세지나 알림이 한도초과로 제거 될 수 있습니다.</SettingsArchiveGeneralTip>
  <SettingsReset>설정 초기화</SettingsReset>
  <UITicks>{0} UI 틱</UITicks>
  <DlgTitleRestart>재시작 필요</DlgTitleRestart>
  <DlgTextRestartNotice>변경 사항을 적용하기 위해 게임을 다시 시작해야 합니다.

모드 설정 페이지를 벗어나면 게임이 다시 시작됩니다.</DlgTextRestartNotice>
  <DlgTextRestartRequest>RuntimeGC 설정이 변경되었으며 해당 변경사항을 적용하기 위해선 게임을 다시 시작해야 합니다.

지금 바로 림월드를 재시작하시겠습니까?</DlgTextRestartRequest>
  <UndoChange>변경 취소</UndoChange>
  <RuntimeGCTitle>RuntimeGC 게임 클리너</RuntimeGCTitle>
  <RuntimeGCVer>{0} 버전</RuntimeGCVer>
  <MainTabWindowDescription>이 탭에는 어려가지 유용한 기능이 포함되어 있습니다. 이 탭으로 현재 게임을 최적화하거나 수정하십시오.</MainTabWindowDescription>
  <BtnTextGCWP>게임 내 캐릭터 정리</BtnTextGCWP>
  <BtnTextGCV>정리(개발자 모드 전용)</BtnTextGCV>
  <BtnTextFix>응급 처치</BtnTextFix>
  <BtnTextAddOn>더 많은 정리</BtnTextAddOn>
  <BtnTextQB>빠른 작업</BtnTextQB>
  <BtnTextSysGC>메모리 정리</BtnTextSysGC>
  <DlgTextGC>살아있는 캐릭터: {0} -> {1}
죽은 캐릭터:  {2} -> {3}

삭제된 캐릭터： {4}</DlgTextGC>
  <DlgTextGCAdvice1>불필요한 캐릭터가 전부 제거되었습니다.
한동안은 해당 버튼을 다시 누를 필요가 없습니다.</DlgTextGCAdvice1>
  <DlgTextGCAdvice2>제거 가능한 캐릭터가 아직 {0}명 남아있습니다.
완벽한 삭제를 위해 해당 버튼을 한번 더 누르는 것을 권장합니다.</DlgTextGCAdvice2>
  <DlgTextGCV>RuntimeGC: 디버그 로그에서 자세한 정보를 확인 할 수 있습니다.</DlgTextGCV>
  <MMTip>

.NET VM 사용량: {0:F2} Mb
Unity 프레임워크와 게임 내부의 메모리는 포함되지 않습니다.</MMTip>
  <DlgArchiveTitle>RuntimeGC 게임 내 캐릭터 정리 로그</DlgArchiveTitle>
  <MsgModMetaDataCleaned>{0}개 모드의 {1}개 데이터를 정리하였습니다.</MsgModMetaDataCleaned>
  <MsgLanguageDataCleaned>사용되지 않는 {0}개 언어어와 {1}개의 번역 데이터가 삭제되었습니다.</MsgLanguageDataCleaned>
  <MsgDefPackageCleaned>{0}개의 DefPackage 정보가 삭제되었습니다.</MsgDefPackageCleaned>
</LanguageData>