<?xml version="1.0" encoding="utf-8"?>
<LanguageData>
  <CMCTechlvl1.label>무기 기초</CMCTechlvl1.label>
  <CMCTechlvl1.description>C.M.C.에서 설계한 기본 무기를 제작합니다.</CMCTechlvl1.description>
  <CMCTechlvl2.label>고급 충전 탄</CMCTechlvl2.label>
  <CMCTechlvl2.description>더 높은 발사 속도와 정확도를 가진 2세대 충전 무기를 제작합니다.</CMCTechlvl2.description>
  <CMCLaserS.label>파티클 랜스</CMCLaserS.label>
  <CMCLaserS.description>고에너지 입자를 단일 목표물에 방출하는 에너지 무기를 제작합니다.</CMCLaserS.description>
  <CMCLaserP.label>표준 레이저 무기</CMCLaserP.label>
  <CMCLaserP.description>발사 속도가 높고 정확도가 우수한 경량 펄스 레이저 무기를 제작합니다. 동시에 여러 적을 공격할 수 있습니다.</CMCLaserP.description>
  <CMCLaserPHeavy.label>고급 레이저 무기</CMCLaserPHeavy.label>
  <CMCLaserPHeavy.description>발사 속도가 높고 정확도가 우수한 중량 펄스 레이저 무기를 제작합니다. 동시에 여러 적을 공격할 수 있습니다.</CMCLaserPHeavy.description>
  <SLProject.label>【SL 프로젝트】</SLProject.label>
  <SLProject.description>근처 별에서 나오는 빛이 미세 포털 게이트를 통해 방향이 전환되고 다른 파장의 레이저 빔으로 굴절됩니다.</SLProject.description>
  <CMCTechlvl3.label>개별 중화기 I</CMCTechlvl3.label>
  <CMCTechlvl3.description>C.M.C.에서 설계한 기본 차량 및 보병 대항 무기를 제작합니다.</CMCTechlvl3.description>
  <CMCTechlvl4.label>개별 중화기 II</CMCTechlvl4.label>
  <CMCTechlvl4.description>C.M.C.에서 설계한 고급 차량 및 보병 대항 무기를 제작합니다.</CMCTechlvl4.description>
  <CMCTechlvl4S.label>전문화된 무기 기술</CMCTechlvl4S.label>
  <CMCTechlvl4S.description>C.M.C.에서 설계한 프로토타입 무기.</CMCTechlvl4S.description>
  <CMCmeleeI.label>근접 무기 I</CMCmeleeI.label>
  <CMCmeleeI.description>기본 우주 근접 무기를 제작합니다.</CMCmeleeI.description>
  <CMCmeleeII.label>근접 무기 II</CMCmeleeII.label>
  <CMCmeleeII.description>고급 우주 근접 무기를 제작합니다.</CMCmeleeII.description>
  <TTproject.label>【TT 프로젝트】</TTproject.label>
  <TTproject.description>우리 과학자들은 마침내 우주선의 무기를 소형화하는 데 성공했고, 이제 적의 쉴드와 중갑옷도 더 이상 우리를 막을 수 없습니다.</TTproject.description>
  <TTprojectII.label>TT 수정</TTprojectII.label>
  <TTprojectII.description>자아 핵 이식 및 개선된 제로포인트 반응기가 파티클 빔의 파괴력을 더욱 증대시킵니다.</TTprojectII.description>
  <XMproject.label>【XM 프로젝트】</XMproject.label>
  <XMproject.description>재료 과학의 혁신을 통해 유도 초음속 소구경 발사체를 개발할 수 있게 되었습니다.</XMproject.description>
  <XMprojectII.label>XM 수정</XMprojectII.label>
  <XMprojectII.description>안정화 된 반엔트로피 물질이 탄환 크기의 용기에 저장되어 소형 발사체가 중갑을 관통하고 심각한 피해를 입힐 수 있습니다.</XMprojectII.description>
  <ZRproject.label>【ZR 프로젝트】</ZRproject.label>
  <ZRproject.description>인공 중력장을 통해 형성되고 발사된 빛나는 플라즈마 볼이 연기 자국을 남기며 접촉 시 파괴적인 힘을 발휘합니다.</ZRproject.description>
  <ZRprojectII.label>ZR 수정</ZRprojectII.label>
  <ZRprojectII.description>이제 과잉 살상은 우리 사전에 없습니다.</ZRprojectII.description>
  <CMCRlvl1.label>T1 개조 기술</CMCRlvl1.label>
  <CMCRlvl1.description>메카 기술을 기반으로 기본 개조 충전 무기를 제작합니다.</CMCRlvl1.description>
  <CMCRlvl2.label>T2 개조 기술</CMCRlvl2.label>
  <CMCRlvl2.description>메카 기술을 기반으로 고급 개조 스마트 총을 제작합니다.</CMCRlvl2.description>
  <CMCAR.label>T3 개조 기술</CMCAR.label>
  <CMCAR.description>첨단 메카노이드 기술에 대한 더 깊은 이해를 바탕으로 전장을 적응시키기 위해 우리의 무기를 제작했습니다.</CMCAR.description>
  <CMCGunTurretsbasic.label>기본 포탑 기술</CMCGunTurretsbasic.label>
  <CMCGunTurretsbasic.description>기본 CMC 포탑을 제작합니다.</CMCGunTurretsbasic.description>
  <CMCGunTurrets.label>고급 포탑 기술</CMCGunTurrets.label>
  <CMCGunTurrets.description>고급 CMC 포탑을 제작합니다.</CMCGunTurrets.description>
  <CMCShield.label>고급 방어 기술</CMCShield.label>
  <CMCShield.description>포스 필드 쉴드와 장거리 순항 미사일을 포함한 고급 방어 시설을 구축합니다.</CMCShield.description>
  <CMCarmor.label>경량 나노 아머</CMCarmor.label>
  <CMCarmor.description>CMC 옷과 경량 갑옷을 제작합니다.</CMCarmor.description>
  <CMCarmorII.label>중량 파워 아머</CMCarmorII.label>
  <CMCarmorII.description>CMC 파워 아머와 개인 쉴드를 제작합니다.</CMCarmorII.description>
  <CMCarmorIII.label>전투 메카나이터 아머</CMCarmorIII.label>
  <CMCarmorIII.description>대역폭이 개선된 전투 메카나이터 아머를 제작합니다.</CMCarmorIII.description>
  <CMCBio.label>CMC 전투 칩</CMCBio.label>
  <CMCBio.description>전문화된 기능을 가진 전투 칩을 제작합니다.</CMCBio.description>
  <CMCPowerI.label>CMC 파워 I</CMCPowerI.label>
  <CMCPowerI.description>CMC 기본 전력 기술</CMCPowerI.description>
  <CMCPowerII.label>CMC 파워 II</CMCPowerII.label>
  <CMCPowerII.description>CMC 표준 전력 기술</CMCPowerII.description>
  <CMCProductionI.label>CMC 자동 생산 I</CMCProductionI.label>
  <CMCProductionI.description>CMC는 인간을 반복적인 작업에서 해방시키고 창의적인 작업으로 전환시키는 것을 목표로 합니다. 이 시리즈의 기술은 이 목표를 달성하기 위해 개발되었습니다.</CMCProductionI.description>
</LanguageData>