<?xml version="1.0" encoding="UTF-8"?>
<LanguageData>
  
  <!-- EN: hiking staff -->
  <Kiiro_Alpenstock.label>등산용 막대</Kiiro_Alpenstock.label>
  <!-- EN: A portable hiking staff that helps traverse rough terrain and slightly increases travel speed in caravan. -->
  <Kiiro_Alpenstock.description>거친 땅을 지나는 데 도움이 되는 등산용 막대. 상단의 속도를 늘려줍니다.</Kiiro_Alpenstock.description>
  
  <!-- EN: jerky pouch -->
  <Kiiro_CuringSnackBag.label>말린 고기 가방</Kiiro_CuringSnackBag.label>
  <!-- EN: A wearable pouch for carrying jerky. Quickly consuming the jerky and slightly restores hunger. -->
  <Kiiro_CuringSnackBag.description>말린 고기를 담을 수 있는 작은 가방. 약간의 허기를 달래는 데 도움이 됩니다.</Kiiro_CuringSnackBag.description>
  <!-- EN: Jerky -->
  <Kiiro_CuringSnackBag.comps.CompApparelReloadable.chargeNoun>말린 고기</Kiiro_CuringSnackBag.comps.CompApparelReloadable.chargeNoun>
  <!-- EN: on cooldown -->
  <Kiiro_CuringSnackBag.comps.CompApparelReloadable.cooldownGerund>재사용 대기중</Kiiro_CuringSnackBag.comps.CompApparelReloadable.cooldownGerund>
  <!-- EN: jerky pouch -->
  <Kiiro_CuringSnackBag.verbs.Verb_Job.label>말린 고기</Kiiro_CuringSnackBag.verbs.Verb_Job.label>
  
  <!-- EN: emergency bandage -->
  <Kiiro_EmergencyBandage.label>비상 붕대</Kiiro_EmergencyBandage.label>
  <!-- EN: A portable bandage for basic first aid. Bandaging a target will heal three random wounds with low quality. Consumes mixed herbal. Bandaging speed and quality are affected by the wearer's medical skill. -->
  <Kiiro_EmergencyBandage.description>기초적인 응급 처치를 위한 붕대입니다. 대상은 3개의 상처를 낮은 품질로 치료될 것이며 속도는 착용자의 의학 수준에 영향받습니다. 형개 혼합 생약을 사용합니다.  </Kiiro_EmergencyBandage.description>
  <!-- EN: bandage -->
  <Kiiro_EmergencyBandage.comps.CompApparelReloadable.chargeNoun>붕대</Kiiro_EmergencyBandage.comps.CompApparelReloadable.chargeNoun>
  <!-- EN: on cooldown -->
 <Kiiro_EmergencyBandage.comps.CompApparelReloadable.cooldownGerund>재사용 대기중</Kiiro_EmergencyBandage.comps.CompApparelReloadable.cooldownGerund>
  <!-- EN: emergency bandage -->
  <Kiiro_EmergencyBandage.verbs.Verb_EmergencyTend.label>비상 붕대</Kiiro_EmergencyBandage.verbs.Verb_EmergencyTend.label>
  
  <!-- EN: Herbal book -->
  <Kiiro_HerbalBook.label>약초학 지식 책</Kiiro_HerbalBook.label>
  <!-- EN: A handwritten book containing knowledge about various herbs, compiled by many barefoot doctors and herbalists. Increases the carrier's medical skill. -->
  <Kiiro_HerbalBook.description>손으로 쓰인 약초학 지식 책입니다. 이 책은 수많은 의사와 약초학 전문가들에 의해 쓰여졌습니다. 착용자의 치료 효과를 개선합니다.</Kiiro_HerbalBook.description>
  
  <!-- EN: jade bracelet -->
  <Kiiro_JadeBracelet.label>비취옥 팔찌</Kiiro_JadeBracelet.label>
  <!-- EN: A bracelet made from finely polished jade. -->
  <Kiiro_JadeBracelet.description>잘 다듬어진 비취옥으로 만든 팔찌입니다.</Kiiro_JadeBracelet.description>
  
  <!-- EN: jade pendant, -->
  <Kiiro_JadePendant.label>비취옥 펜던트</Kiiro_JadePendant.label>
  <!-- EN: A pendant made from finely polished jade, strung on a silk cord. -->
  <Kiiro_JadePendant.description>비단 실줄에 잘 다듬어진 비취옥을 매달은 펜던트입니다.</Kiiro_JadePendant.description>
  
  <!-- EN: sharpening stone -->
  <Kiiro_KnifeStone.label>숫돌</Kiiro_KnifeStone.label>
  <!-- EN: A portable sharpening stone.\n\nTemporarily increases the wearer's melee damage with each use. Consumes steel. -->
  <Kiiro_KnifeStone.description>작은 숫돌입니다. 사용하면 착용자의 근접 공격력을 개선합니다. 강철을 사용합니다.</Kiiro_KnifeStone.description>
  <!-- EN: Sharpen -->
  <Kiiro_KnifeStone.comps.CompApparelReloadable.chargeNoun>숫돌</Kiiro_KnifeStone.comps.CompApparelReloadable.chargeNoun>
  <!-- EN: on cooldown -->
  <Kiiro_KnifeStone.comps.CompApparelReloadable.cooldownGerund>재사용 대기중</Kiiro_KnifeStone.comps.CompApparelReloadable.cooldownGerund>
  <!-- EN: sharpening stone -->
  <Kiiro_KnifeStone.verbs.Verb_Job.label>숫돌</Kiiro_KnifeStone.verbs.Verb_Job.label>
  
  <!-- EN: modern medicine textbook-->
  <Kiiro_ModernMedicine.label>현대 의학 교과서</Kiiro_ModernMedicine.label>
  <!-- EN: A book containing scientific medical knowledge, from general health care to the treatment of complex diseases. Includes a handwritten notebook for taking notes. Greatly increases the carrier's medical skill. -->
  <Kiiro_ModernMedicine.description>일반적인 건강 관리부터 복잡한 질병 치료에 관한 내용이 담긴 책입니다. 누군가 직접 필기한 흔적이 남아 있습니다. 착용자의 치료 효과를 상당히 개선합니다.</Kiiro_ModernMedicine.description>
  
  <!-- EN: pocket watch -->
  <Kiiro_PocketWatch.label>회중 시계</Kiiro_PocketWatch.label>
  <!-- EN: A small and portable timekeeping device. Wearing it can subtly increase the wearer's work efficiency. -->
  <Kiiro_PocketWatch.description>시간 관리에 도움이 되는 작은 회중 시계입니다. 착용자의 전역 작업 속도를 개선합니다.</Kiiro_PocketWatch.description>
  
  <!-- EN: delicate pocket watch -->
  <Kiiro_PocketWatch_Delicate.label>세련된 회중 시계</Kiiro_PocketWatch_Delicate.label>
  <!-- EN: A delicate, small, portable timekeeping device. Wearing it can subtly increase the wearer's work efficiency. -->
  <Kiiro_PocketWatch_Delicate.description>시간 관리에 도움이 되는 세련된 회중 시계입니다. 착용자의 전역 작업 속도를 개선합니다.</Kiiro_PocketWatch_Delicate.description>
  
  <!-- EN: screwdriver set -->
  <Kiiro_ScrewdriverSet.label>스크루드라이버 세트</Kiiro_ScrewdriverSet.label>
  <!-- EN: A set of screwdrivers of various sizes and diameters. Increases the wearer's mechanical work efficiency. -->
  <Kiiro_ScrewdriverSet.description>여러가지 크기의 스크루드라이버 세트입니다. 착용자의 메카노이드 관련 작업 효율을 개선합니다.</Kiiro_ScrewdriverSet.description>
  
  <!-- EN: survival guide -->
  <Kiiro_SurvivalGuide.label>생존 수칙</Kiiro_SurvivalGuide.label>
  <!-- EN: A guidebook on how to find food and survive in the wild. The pages are waterproofed and the cover is made of thick leather. -->
  <Kiiro_SurvivalGuide.description>야생에서 먹을 것을 찾고, 살아 남는 방법을 다룬 책입니다. 방수 처리가 되어 있으며 두꺼운 가죽으로 마감되어 있습니다. 착용자의 식량 채집량을 개선합니다.</Kiiro_SurvivalGuide.description>
  
  <Kiiro_RefinedFishingLine.label>정제된 낚싯줄</Kiiro_RefinedFishingLine.label>
  <Kiiro_RefinedFishingLine.description>낚시에 도움이 되는 견고한 낚싯줄입니다. 착용자의 낚시 속도와 어획량을 개선합니다.</Kiiro_RefinedFishingLine.description>
  
  <!-- EN: sewing kit -->
  <Kiiro_TailorSet.label>재봉 도구</Kiiro_TailorSet.label>
  <!-- EN: A full set of portable sewing tools that can be used to repair clothing while carrying. \n\nSelect the carrier wearing clothing in the lowest percentage of durability for its return to a certain durability. More than 75% of the most durable clothing is beyond repair. -->
  <Kiiro_TailorSet.description>작은 재봉 도구입니다. 착용자는 입은 옷에서 내구성이 가장 낮은 옷을 수리할 수 있습니다. 75% 이상의 의류는 수리할 수 없습니다. </Kiiro_TailorSet.description>
  <!-- EN: Repair -->
  <Kiiro_TailorSet.comps.CompApparelReloadable.chargeNoun>재봉 도구</Kiiro_TailorSet.comps.CompApparelReloadable.chargeNoun>
  <!-- EN: on cooldown -->
  <Kiiro_TailorSet.comps.CompApparelReloadable.cooldownGerund>재사용 대기중</Kiiro_TailorSet.comps.CompApparelReloadable.cooldownGerund>
  <!-- EN: sewing kit -->
  <Kiiro_TailorSet.verbs.Verb_MendApparel.label>재봉 도구</Kiiro_TailorSet.verbs.Verb_MendApparel.label>
  
  <!-- EN: tile tool set -->
  <Kiiro_TileToolSet.label>타일 공구</Kiiro_TileToolSet.label>
  <!-- EN: A set of handy construction tools, including a troweland a bricklayer's knife. Increases the wearer's construction work efficiency. -->
  <Kiiro_TileToolSet.description>퍼티 작업용 칼과 모종삽을 포함하는 공구. 착용자의 건설 속도를 개선합니다.</Kiiro_TileToolSet.description>
  
  <!-- EN: multi-tool set -->
  <Kiiro_ToolSet.label>다용도구</Kiiro_ToolSet.label>
  <!-- EN: A versatile tool set that increases the wearer's overall work efficiency. -->
  <Kiiro_ToolSet.description>작은 다용도구입니다. 착용자의 채굴, 재배, 건설 속도를 개선합니다.</Kiiro_ToolSet.description>
  
</LanguageData>