<?xml version="1.0" encoding="utf-8"?>
<LanguageData>
  <BEWH_TendedByApothecary.stages.0.label>{0}에게 치료 받음</BEWH_TendedByApothecary.stages.0.label>
  <BEWH_TendedByApothecary.stages.0.description>아포세카리에게 치료를 받았습니다!</BEWH_TendedByApothecary.stages.0.description>
  <BEWH_InteractedWithChampion.stages.0.label>챕터 챔피언과 대화</BEWH_InteractedWithChampion.stages.0.label>
  <BEWH_InteractedWithChampion.stages.0.description>챕터 챔피언과 이야기를 나눴습니다!</BEWH_InteractedWithChampion.stages.0.description>
  <BEWH_InteractedWithChampionMood.stages.0.label>챕터 챔피언과 대화</BEWH_InteractedWithChampionMood.stages.0.label>
  <BEWH_InteractedWithChampionMood.stages.0.description>챕터 챔피언과 이야기를 나눴습니다!</BEWH_InteractedWithChampionMood.stages.0.description>
  <BEWH_TendedByMedicae.stages.0.label>{0}에게 치료 받음</BEWH_TendedByMedicae.stages.0.label>
  <BEWH_TendedByMedicae.stages.0.description>메디카에게 치료를 받았습니다!</BEWH_TendedByMedicae.stages.0.description>
  <BEWH_Psyker_Respected.stages.0.label>사이커</BEWH_Psyker_Respected.stages.0.label>
  <BEWH_Psyker_Respected.stages.0.description>사이커가 된 것은 큰 혜택입니다.</BEWH_Psyker_Respected.stages.0.description>.
  <BEWH_Psyker_Respected_Social.stages.0.label>사이커</BEWH_Psyker_Respected_Social.stages.0.label>
  <BEWH_Psyker_Horrible.stages.0.label>사이커</BEWH_Psyker_Horrible.stages.0.label>
  <BEWH_Psyker_stages.0.description>사이커가 된 것은 저에게 내려진 저주입니다.</BEWH_Psyker_stages.0.description>.
  <BEWH_Psyker_Horrible_Social.stages.0.label>사이커</BEWH_Psyker_Horrible_Social.stages.0.label>
  <BEWH_Mutation_Respected.stages.0.label>변이되지 않음</BEWH_Mutation_Respected.stages.0.label>
  <BEWH_Mutation_Respected.stages.0.description>나는 아직 신으로부터 선물을 받지 못했습니다.</BEWH_Mutation_Respected.stages.0.description>
  <BEWH_Mutation_Respected.stages.1.label>약간 변이됨</BEWH_Mutation_Respected.stages.1.label>
  <BEWH_Mutation_Respected.stages.1.description>저는 신이 주신 선물, 진정한 축복을 받았습니다.</BEWH_Mutation_Respected.stages.1.description>
  <BEWH_Mutation_Respected.stages.2.label>변이됨</BEWH_Mutation_Respected.stages.2.label>
  <BEWH_Mutation_Respected.stages.2.description>저는 신으로부터 여러 가지 선물을 받았는데, 이는 진정한 축복입니다.</BEWH_Mutation_Respected.stages.2.description>
  <BEWH_Mutation_Respected.stages.3.label>크게 변이됨</BEWH_Mutation_Respected.stages.3.label>
  <BEWH_Mutation_Respected.stages.3.description>저는 신으로부터 많은 선물을 받았는데, 이는 진정한 축복입니다.</BEWH_Mutation_Respected.stages.3.description>
  <BEWH_Mutation_Respected_Social.stages.0.label>변이되지 않음</BEWH_Mutation_Respected_Social.stages.0.label>
  <BEWH_Mutation_Respected_Social.stages.1.label>약간 변이됨</BEWH_Mutation_Respected_Social.stages.1.label>
  <BEWH_Mutation_Respected_Social.stages.2.label>변이됨</BEWH_Mutation_Respected_Social.stages.2.label>
  <BEWH_Mutation_Respected_Social.stages.3.label>크게 변이됨</BEWH_Mutation_Respected_Social.stages.3.label>
  <BEWH_Mutation_Horrible.stages.0.label>변이되지 않음</BEWH_Mutation_Horrible.stages.0.label>
  <BEWH_Mutation_Horrible.stages.0.description>내 몸은 이단적인 돌연변이로부터 순수합니다.</BEWH_Mutation_Horrible.stages.0.description>
  <BEWH_Mutation_Horrible.stages.1.label>약간 변이됨</BEWH_Mutation_Horrible.stages.1.label>
  <BEWH_Mutation_Horrible.stages.1.description>나는 신들로부터 저주를 받았습니다.</BEWH_Mutation_Horrible.stages.1.description>
  <BEWH_Mutation_Horrible.stages.2.label>변이됨</BEWH_Mutation_Horrible.stages.2.label>
  <BEWH_Mutation_Horrible.stages.2.description>신들의 저주를 받았어요, 정말 잔인한 농담이네요.</BEWH_Mutation_Horrible.stages.2.description>
  <BEWH_Mutation_Horrible.stages.3.label>크게 변이됨</BEWH_Mutation_Horrible.stages.3.label>
  <BEWH_Mutation_Horrible.stages.3.description>나는 신들에게 심한 저주를 받았으며, 이제 죽음만이 나의 구원입니다.</BEWH_Mutation_Horrible.stages.3.description>
  <BEWH_Mutation_Horrible_Social.stages.0.label>변이되지 않음</BEWH_Mutation_Horrible_Social.stages.0.label>
  <BEWH_Mutation_Horrible_Social.stages.1.label>약간 변이됨</BEWH_Mutation_Horrible_Social.stages.1.label>
  <BEWH_Mutation_Horrible_Social.stages.2.label>변이됨</BEWH_Mutation_Horrible_Social.stages.2.label>
  <BEWH_Mutation_Horrible_Social.stages.3.label>크게 변이됨</BEWH_Mutation_Horrible_Social.stages.3.label>
  <BEWH_Mutation_Respected_Specific.stages.0.label>잘못된 변이</BEWH_Mutation_Respected_Specific.stages.0.label>
  <BEWH_Mutation_Respected_Specific.stages.0.description>다른 신의 변이가 내 신의 변이보다 더 많이 퍼졌습니다.</BEWH_Mutation_Respected_Specific.stages.0.description>
  <BEWH_Mutation_Respected_Specific.stages.1.label>변이되지 않음</BEWH_Mutation_Respected_Specific.stages.1.label>
  <BEWH_Mutation_Respected_Specific.stages.1.description>나는 아직 신으로부터 선물을 받지 못했습니다.</BEWH_Mutation_Respected_Specific.stages.1.description>
  <BEWH_Mutation_Respected_Specific.stages.2.label>약간 변이됨</BEWH_Mutation_Respected_Specific.stages.2.label>
  <BEWH_Mutation_Respected_Specific.stages.2.description>저는 신이 주신 선물, 진정한 축복을 받았습니다.</BEWH_Mutation_Respected_Specific.stages.2.description>
  <BEWH_Mutation_Respected_Specific.stages.3.label>변이됨</BEWH_Mutation_Respected_Specific.stages.3.label>
  <BEWH_Mutation_Respected_Specific.stages.3.description>저는 신으로부터 진정한 축복인 여러 가지 선물을 받았습니다.</BEWH_Mutation_Respected_Specific.stages.3.description>
  <BEWH_Mutation_Respected_Specific.stages.4.label>심하게 변이됨</BEWH_Mutation_Respected_Specific.stages.4.label>
  <BEWH_Mutation_Respected_Specific.stages.4.description>저는 신으로부터 많은 선물을 받았으며, 이는 진정한 축복입니다.</BEWH_Mutation_Respected_Specific.stages.4.description>
  <BEWH_Mutation_Respected_Social_Specific.stages.0.label>잘못된 변이</BEWH_Mutation_Respected_Social_Specific.stages.0.label>
  <BEWH_Mutation_Respected_Social_Specific.stages.1.label>변이되지 않음</BEWH_Mutation_Respected_Social_Specific.stages.1.label>
  <BEWH_Mutation_Respected_Social_Specific.stages.2.label>약간 변이됨</BEWH_Mutation_Respected_Social_Specific.stages.2.label>
  <BEWH_Mutation_Respected_Social_Specific.stages.3.label>변이됨</BEWH_Mutation_Respected_Social_Specific.stages.3.label>
  <BEWH_Mutation_Respected_Social_Specific.stages.4.label>크게 변이됨</BEWH_Mutation_Respected_Social_Specific.stages.4.label>
</LanguageData>