<?xml version="1.0" encoding="utf-8"?>
<LanguageData>
  <Axolotl_CultSlave.label>적혈종 제물</Axolotl_CultSlave.label>
  <Axolotl_CultDisciple.label>적혈종 제자</Axolotl_CultDisciple.label>
  <Axolotl_CultProtector.label>적혈종 호법</Axolotl_CultProtector.label>
  <Axolotl_CultElder.label>적혈종 장로</Axolotl_CultElder.label>
  <Axolotl_CrimsonBloodMystic.label>적혈종 방술사</Axolotl_CrimsonBloodMystic.label>
  <Axolotl_CultMaster.label>적혈종 장문</Axolotl_CultMaster.label>
  <Axolotl_CrimsonBloodGuardian.label>적혈종 혈위</Axolotl_CrimsonBloodGuardian.label>
  <Axolotl_CultGrandmaster.label>적혈종 종주</Axolotl_CultGrandmaster.label>
</LanguageData>